membrane_kymograph/__init__.py
membrane_kymograph/_version.py
membrane_kymograph/config.py
membrane_kymograph/correlation.py
membrane_kymograph/gui.py
membrane_kymograph/kymohelpers.py
membrane_kymograph/parulamap.py
membrane_kymograph/processor.py
membrane_kymograph/utils.py
membrane_kymograph/tests/__init__.py
membrane_kymograph/tests/test_correlation.py
membrane_kymograph/tests/test_kymohelpers.py
membrane_kymograph/tests/test_processor.py
membrane_kymograph-0.0.3.dist-info/licenses/LICENSE
membrane_kymograph-0.0.3.dist-info/METADATA
membrane_kymograph-0.0.3.dist-info/WHEEL
membrane_kymograph-0.0.3.dist-info/entry_points.txt
membrane_kymograph-0.0.3.dist-info/top_level.txt
membrane_kymograph-0.0.3.dist-info/RECORD
