Metadata-Version: 2.4
Name: membrane-kymograph
Version: 0.0.3
Summary: A GUI-based cross-platform tool for generating membrane kymographs from live-cell time-lapse microscopy images
Home-page: https://github.com/tatsatb/membrane-kymograph-generator
Download-URL: https://github.com/tatsatb/membrane-kymograph-generator/releases/latest
Author: Tatsat Banerjee
License: GPL-3.0-or-later
Project-URL: Bug Reports, https://github.com/tatsatb/membrane-kymograph-generator/issues
Project-URL: Source, https://github.com/tatsatb/membrane-kymograph-generator
Keywords: microscopy kymograph cell-biology fluorescence image-processing membrane-dynamics
Classifier: Intended Audience :: Science/Research
Classifier: Topic :: Scientific/Engineering :: Bio-Informatics
Classifier: Topic :: Scientific/Engineering :: Image Processing
Classifier: Programming Language :: Python :: 3
Classifier: Programming Language :: Python :: 3.10
Classifier: Programming Language :: Python :: 3.11
Classifier: Programming Language :: Python :: 3.12
Classifier: Programming Language :: Python :: 3.13
Classifier: Operating System :: OS Independent
Requires-Python: >=3.10,<3.14
License-File: LICENSE
Requires-Dist: circle-fit==0.2.1
Requires-Dist: contourpy==1.3.2
Requires-Dist: cycler==0.12.1
Requires-Dist: et_xmlfile==2.0.0
Requires-Dist: fonttools==4.60.1
Requires-Dist: future==1.0.0
Requires-Dist: imageio==2.37.0
Requires-Dist: joblib==1.5.2
Requires-Dist: kiwisolver==1.4.9
Requires-Dist: lazy_loader==0.4
Requires-Dist: matplotlib==3.10.7
Requires-Dist: networkx==3.4.2
Requires-Dist: numpy==2.2.6
Requires-Dist: opencv-python==4.12.0.88
Requires-Dist: openpyxl==3.1.5
Requires-Dist: packaging==25.0
Requires-Dist: pandas==2.3.3
Requires-Dist: patsy==1.0.2
Requires-Dist: pillow==11.3.0
Requires-Dist: pyparsing==3.2.5
Requires-Dist: python-dateutil==2.9.0.post0
Requires-Dist: pytz==2025.2
Requires-Dist: scikit-image==0.25.2
Requires-Dist: scikit-learn==1.7.2
Requires-Dist: scipy==1.15.3
Requires-Dist: seaborn==0.13.2
Requires-Dist: shapely==2.1.2
Requires-Dist: six==1.17.0
Requires-Dist: statsmodels==0.14.5
Requires-Dist: threadpoolctl==3.6.0
Requires-Dist: tifffile==2025.5.10
Requires-Dist: tiffile==2018.10.18
Requires-Dist: ttkbootstrap==1.16.0
Requires-Dist: tzdata==2025.2
Provides-Extra: dev
Requires-Dist: pytest>=7.0; extra == "dev"
Requires-Dist: pytest-cov>=4.0; extra == "dev"
Requires-Dist: black>=22.0; extra == "dev"
Requires-Dist: flake8>=5.0; extra == "dev"
Requires-Dist: mypy>=1.0; extra == "dev"
Dynamic: author
Dynamic: classifier
Dynamic: description
Dynamic: description-content-type
Dynamic: download-url
Dynamic: home-page
Dynamic: keywords
Dynamic: license
Dynamic: license-file
Dynamic: project-url
Dynamic: provides-extra
Dynamic: requires-dist
Dynamic: requires-python
Dynamic: summary
